indico_ursh/__init__.py
indico_ursh/blueprint.py
indico_ursh/controllers.py
indico_ursh/plugin.py
indico_ursh/util.py
indico_ursh/views.py
indico_ursh/static/dist/manifest.json
indico_ursh/static/dist/js/main.b412feb2.bundle.js
indico_ursh/static/dist/js/main.b412feb2.bundle.js.map
indico_ursh/static/dist/js/monaco.css.worker.js
indico_ursh/static/dist/js/monaco.css.worker.js.map
indico_ursh/static/dist/js/monaco.editor.worker.js
indico_ursh/static/dist/js/monaco.editor.worker.js.map
indico_ursh/static/dist/js/monaco.html.worker.js
indico_ursh/static/dist/js/monaco.html.worker.js.map
indico_ursh/templates/ursh_custom_shortener_page.html
indico_ursh/templates/ursh_dropdown.html
indico_ursh/templates/ursh_footer.html
indico_ursh/templates/ursh_link.html
indico_ursh/templates/ursh_shortener_page.html
indico_ursh/translations/messages-js.pot
indico_ursh/translations/messages.pot
indico_ursh/translations/cs_CZ/LC_MESSAGES/messages.mo
indico_ursh/translations/cs_CZ/LC_MESSAGES/messages.po
indico_ursh/translations/de_DE/LC_MESSAGES/messages.mo
indico_ursh/translations/de_DE/LC_MESSAGES/messages.po
indico_ursh/translations/en_CA/LC_MESSAGES/messages.mo
indico_ursh/translations/en_CA/LC_MESSAGES/messages.po
indico_ursh/translations/en_GB/LC_MESSAGES/messages.mo
indico_ursh/translations/en_GB/LC_MESSAGES/messages.po
indico_ursh/translations/es_ES/LC_MESSAGES/messages.mo
indico_ursh/translations/es_ES/LC_MESSAGES/messages.po
indico_ursh/translations/fr_FR/LC_MESSAGES/messages.mo
indico_ursh/translations/fr_FR/LC_MESSAGES/messages.po
indico_ursh/translations/hu_HU/LC_MESSAGES/messages.mo
indico_ursh/translations/hu_HU/LC_MESSAGES/messages.po
indico_ursh/translations/it_IT/LC_MESSAGES/messages.mo
indico_ursh/translations/it_IT/LC_MESSAGES/messages.po
indico_ursh/translations/ja_JP/LC_MESSAGES/messages.mo
indico_ursh/translations/ja_JP/LC_MESSAGES/messages.po
indico_ursh/translations/mn_MN/LC_MESSAGES/messages.mo
indico_ursh/translations/mn_MN/LC_MESSAGES/messages.po
indico_plugin_ursh-3.3.2.dist-info/METADATA
indico_plugin_ursh-3.3.2.dist-info/WHEEL
indico_plugin_ursh-3.3.2.dist-info/entry_points.txt
indico_plugin_ursh-3.3.2.dist-info/RECORD
